{"index":{"links":{"/":[{"source":"/","target":"/notes/Digital-Garden","text":"Digital Garden"}],"/notes/Digital-Garden":[{"source":"/notes/Digital-Garden","target":"/Atomic-Notes","text":"Atomic Notes"}]},"backlinks":{"/Atomic-Notes":[{"source":"/notes/Digital-Garden","target":"/Atomic-Notes","text":"Atomic Notes"}],"/notes/Digital-Garden":[{"source":"/","target":"/notes/Digital-Garden","text":"Digital Garden"}]}},"links":[{"source":"/","target":"/notes/Digital-Garden","text":"Digital Garden"},{"source":"/notes/Digital-Garden","target":"/Atomic-Notes","text":"Atomic Notes"}]}